ondewo/__init__.py
ondewo/survey/__init__.py
ondewo/survey/fhir_pb2.py
ondewo/survey/fhir_pb2.pyi
ondewo/survey/fhir_pb2_grpc.py
ondewo/survey/py.typed
ondewo/survey/survey_pb2.py
ondewo/survey/survey_pb2.pyi
ondewo/survey/survey_pb2_grpc.py
ondewo/survey/client/__init__.py
ondewo/survey/client/client.py
ondewo/survey/client/client_config.py
ondewo/survey/client/services_container.py
ondewo/survey/client/services/__init__.py
ondewo/survey/client/services/fhir.py
ondewo/survey/client/services/survey.py
ondewo_survey_client-2.0.1.dist-info/LICENSE
ondewo_survey_client-2.0.1.dist-info/METADATA
ondewo_survey_client-2.0.1.dist-info/WHEEL
ondewo_survey_client-2.0.1.dist-info/top_level.txt
ondewo_survey_client-2.0.1.dist-info/RECORD
