Metadata-Version: 2.1
Name: ondewo-survey-client
Version: 2.0.1
Summary: ONDEWO Survey (SURVEY) Client library for Python
Home-page: https://github.com/ondewo/ondewo-survey-client-python
Author: ONDEWO GmbH
Author-email: office@ondewo.com
License: UNKNOWN
Platform: UNKNOWN
Classifier: Development Status :: 5 - Production/Stable
Classifier: Intended Audience :: Developers
Classifier: License :: OSI Approved :: Apache Software License
Classifier: Operating System :: OS Independent
Classifier: Programming Language :: Python :: 3.8
Classifier: Programming Language :: Python :: 3.9
Classifier: Programming Language :: Python :: 3.10
Classifier: Programming Language :: Python :: 3.11
Classifier: Programming Language :: Python :: 3.12
Classifier: Topic :: Software Development :: Libraries
Requires-Python: >=3
License-File: LICENSE
Requires-Dist: google-api-core >=2.8.1
Requires-Dist: googleapis-common-protos >=1.56.4
Requires-Dist: grpcio-reflection >=1.47.0
Requires-Dist: grpcio-tools >=1.47.0
Requires-Dist: grpcio >=1.47.0
Requires-Dist: ondewo-client-utils
Requires-Dist: protobuf >=3.13.0
